[
  {
    "is_hate": true,
    "username": "AsaDeMatteo",
    "lang": "en",
    "text": "@realDonaldTrump Keeping guns out of the hands of the mad and irresponsible would be so much more useful than the strawberry milkshakes of insincere sympathy.",
    "full_name": "Asa DeMatteo, Ph.D.",
    "time": "2017-11-15 06:22:38"
  },
  {
    "is_hate": true,
    "username": "HeastyRalph",
    "lang": "en",
    "text": "@Logic_Triumphs @realDonaldTrump His real legacy will be the dismantling of the administrative agencies of the federal government, which was apparently his agenda all along the rest is just to keep the public from seeing that",
    "full_name": "Ralph",
    "time": "2017-11-15 06:22:36"
  },
  {
    "is_hate": true,
    "username": "tracyb115",
    "lang": "en",
    "text": "@realDonaldTrump \"I was angry she was raped, yes that was one thing. But she was so beautiful, I think the mayor should have been first. What a waste,\" ~Duterte \n\n*GREAT WORK* alining us with this monster.\n\n#ResignTrump \nhttps://t.co/NMo4eUUYjY",
    "full_name": "Tracy B",
    "time": "2017-11-15 06:22:34"
  },
  {
    "is_hate": true,
    "username": "cnzsmt",
    "lang": "en",
    "text": "@realDonaldTrump Wrong mass shooting, you \ud83e\udd21#UnfitForOffice #ImpeachTrumpNow #clueless45 #nationalembarassement",
    "full_name": "Cinzia Smith",
    "time": "2017-11-15 06:22:34"
  },
  {
    "is_hate": false,
    "username": "ROSANELLLOLLAR8",
    "lang": "en",
    "text": "@realDonaldTrump \nGlad to have you home",
    "full_name": "ROSANELL LOLLAR",
    "time": "2017-11-15 06:22:33"
  }
]
